emailer.py
package_map.py
shutit.py
shutit_assets.py
shutit_background.py
shutit_class.py
shutit_exam.py
shutit_global.py
shutit_login_stack.py
shutit_module.py
shutit_pexpect.py
shutit_pexpect_session_environment.py
shutit_sendspec.py
shutit_setup.py
shutit_skeleton.py
shutit_threads.py
shutit_util.py
shutit_patterns/__init__.py
shutit_patterns/bash.py
shutit_patterns/docker.py
shutit_patterns/docker_tutorial.py
shutit_patterns/shutitfile.py
shutit_patterns/vagrant.py
shutit_session_setup/__init__.py
shutit_session_setup/vagrant.py
shutit_session_setup/virtualization.py
shutit-1.0.162.dist-info/LICENSE
shutit-1.0.162.dist-info/METADATA
shutit-1.0.162.dist-info/WHEEL
shutit-1.0.162.dist-info/entry_points.txt
shutit-1.0.162.dist-info/top_level.txt
shutit-1.0.162.dist-info/RECORD
