Metadata-Version: 2.1
Name: shutit
Version: 1.0.162
Summary: A programmable automation tool designed for complex builds
Home-page: http://ianmiell.github.io/shutit/
Author: Ian Miell
Author-email: ian.miell@gmail.com
License: MIT
Keywords: Docker pexpect expect automation build
Platform: UNKNOWN
Classifier: Development Status :: 4 - Beta
Classifier: Intended Audience :: Developers
Classifier: Topic :: Software Development :: Build Tools
Classifier: License :: OSI Approved :: MIT License
Classifier: Programming Language :: Python :: 2.7
Requires-Dist: pexpect (>=4.0)
Requires-Dist: jinja2 (>=0.1)
Requires-Dist: texttable (>=0.1)
Requires-Dist: six (>=1.10)
Requires-Dist: future (>=0.15)
Requires-Dist: curtsies (>=0.3.0)
Requires-Dist: cjkwrap
Provides-Extra: dev
Provides-Extra: test
